{
  "queryStats": [
    {
      "id": "stat_1774675018216_6ycv",
      "queryName": "pnl_lineage",
      "success": true,
      "durationMs": 4,
      "timestamp": "2026-03-28T05:16:58.216Z",
      "filters": {}
    },
    {
      "id": "stat_1774675018219_aqlt",
      "queryName": "pnl_lineage",
      "success": true,
      "durationMs": 5,
      "timestamp": "2026-03-28T05:16:58.219Z",
      "filters": {}
    },
    {
      "id": "stat_1774675018365_f47e",
      "queryName": "pnl_lineage",
      "success": true,
      "durationMs": 4,
      "timestamp": "2026-03-28T05:16:58.365Z",
      "filters": {}
    },
    {
      "id": "stat_1774675019943_8rh1",
      "queryName": "pnl_lineage",
      "success": true,
      "durationMs": 7,
      "timestamp": "2026-03-28T05:16:59.943Z",
      "filters": {}
    },
    {
      "id": "stat_1774675020100_mrt1",
      "queryName": "pnl_lineage",
      "success": true,
      "durationMs": 6,
      "timestamp": "2026-03-28T05:17:00.100Z",
      "filters": {}
    },
    {
      "id": "stat_1774675020507_bil5",
      "queryName": "pnl_lineage",
      "success": true,
      "durationMs": 4,
      "timestamp": "2026-03-28T05:17:00.508Z",
      "filters": {}
    },
    {
      "id": "stat_1774675020955_30q0",
      "queryName": "active_users",
      "success": true,
      "durationMs": 2,
      "timestamp": "2026-03-28T05:17:00.955Z",
      "filters": {}
    },
    {
      "id": "stat_1774675021033_7u1v",
      "queryName": "active_users",
      "success": true,
      "durationMs": 2,
      "timestamp": "2026-03-28T05:17:01.033Z",
      "filters": {}
    }
  ]
}
